play/__init__.py
play/cpu_train.py
play/human_train.py
play/human_vs_cpu.py
tictactoe/__init__.py
tictactoe/board.py
tictactoe/game.py
tictactoe/styledprint.py
tictactoe/player/__init__.py
tictactoe/player/human_player.py
tictactoe/player/learner_player.py
tictactoe/player/random_player.py
tictactoe_q_learning-0.0.1.dist-info/LICENSE
tictactoe_q_learning-0.0.1.dist-info/METADATA
tictactoe_q_learning-0.0.1.dist-info/WHEEL
tictactoe_q_learning-0.0.1.dist-info/top_level.txt
tictactoe_q_learning-0.0.1.dist-info/RECORD
