Metadata-Version: 2.1
Name: tictactoe-q-learning
Version: 0.0.1
Summary: tictactoe q-learning system
Home-page: https://github.com/estudos-luanws/tictactoe-q-learning
Author: luanws
Author-email: luan.w.silveira@gmail.com
License: UNKNOWN
Platform: UNKNOWN
Classifier: Programming Language :: Python :: 3
Classifier: License :: OSI Approved :: MIT License
Classifier: Operating System :: OS Independent
Requires-Python: >=3.6
